fibnumber/__init__.py
fibnumber/cmd/fib_numb.py
fibnumber/fib_calcs/__init__.py
fibnumber/fib_calcs/fib_number.py
fibnumber/fib_calcs/fib_numbers.py
fibnumber-0.1.5.dist-info/LICENSE
fibnumber-0.1.5.dist-info/METADATA
fibnumber-0.1.5.dist-info/WHEEL
fibnumber-0.1.5.dist-info/entry_points.txt
fibnumber-0.1.5.dist-info/RECORD
