Metadata-Version: 2.1
Name: fibnumber
Version: 0.1.5
Summary: Calculate fibonacci using a simple program
Author: XettriSomeman
Author-email: bsomeman326@gmail.com
Requires-Python: >=3.8,<4.0
Classifier: Programming Language :: Python :: 3
Classifier: Programming Language :: Python :: 3.8
Classifier: Programming Language :: Python :: 3.9
Classifier: Programming Language :: Python :: 3.10
Classifier: Programming Language :: Python :: 3.11
Provides-Extra: server
Requires-Dist: click (>=8.1.3,<9.0.0)
Requires-Dist: fastapi (>=0.95.1,<0.96.0) ; extra == "server"
